verilog/number_decoder.v
module number_decoder(
   //output
   next_nibble_valid,
   nibble,

   //input
   code,
   this_nibble_valid
);

output next_nibble_valid;
output[3:0] nibble;

input[4:0] code;
input this_nibble_valid;

assign next_nibble_valid = code[4] & this_nibble_valid;
assign nibble = code[3:0] & {4{this_nibble_valid}};


endmodule

verilog/number_brian.v
module number_brian(
   //output
   number,

   //input
   clk,
   resetB,
   enable,
   validNibbles,
   inputNumber
);

output [63:0] number;

input clk;
input resetB;
input enable;
input [16:0] validNibbles;
input [63:0] inputNumber;


wire [63:0] oneNibbleEnabled;
wire [63:0] twoNibblesEnabled;
wire [63:0] threeNibblesEnabled;
wire [63:0] fourNibblesEnabled;
wire [63:0] fiveNibblesEnabled;
wire [63:0] sixNibblesEnabled;
wire [63:0] sevenNibblesEnabled;
wire [63:0] eightNibblesEnabled;
wire [63:0] nineNibblesEnabled;
wire [63:0] tenNibblesEnabled;
wire [63:0] elevenNibblesEnabled;
wire [63:0] twelveNibblesEnabled;
wire [63:0] thirteenNibblesEnabled;
wire [63:0] fourteenNibblesEnabled;
wire [63:0] fifteenNibblesEnabled;
wire [63:0] sixteenNibblesEnabled;

reg [63:0] dataNext;
reg[63:0] number;

assign oneNibbleEnabled = {60'h0,inputNumber[63:60]};
assign twoNibblesEnabled = {56'h0,inputNumber[63:56]};
assign threeNibblesEnabled = {52'h0,inputNumber[63:52]};
assign fourNibblesEnabled = {48'h0,inputNumber[63:48]};
assign fiveNibblesEnabled = {44'h0,inputNumber[63:44]};
assign sixNibblesEnabled = {40'h0,inputNumber[63:40]};
assign sevenNibblesEnabled = {36'h0,inputNumber[63:36]};
assign eightNibblesEnabled = {32'h0,inputNumber[63:32]};
assign nineNibblesEnabled = {28'h0,inputNumber[63:28]};
assign tenNibblesEnabled = {24'h0,inputNumber[63:24]};
assign elevenNibblesEnabled = {20'h0,inputNumber[63:20]};
assign twelveNibblesEnabled = {16'h0,inputNumber[63:16]};
assign thirteenNibblesEnabled = {12'h0,inputNumber[63:12]};
assign fourteenNibblesEnabled = {8'h0,inputNumber[63:8]};
assign fifteenNibblesEnabled = {4'h0,inputNumber[63:4]};
assign sixteenNibblesEnabled = inputNumber[63:0];

always @(validNibbles or oneNibbleEnabled or twoNibblesEnabled or
         threeNibblesEnabled or fourNibblesEnabled or fiveNibblesEnabled or
         sixNibblesEnabled or sevenNibblesEnabled or eightNibblesEnabled or
         nineNibblesEnabled or tenNibblesEnabled or elevenNibblesEnabled or
         twelveNibblesEnabled or thirteenNibblesEnabled or fourteenNibblesEnabled
         or fifteenNibblesEnabled or sixteenNibblesEnabled)
   begin
       dataNext = oneNibbleEnabled;
       if (validNibbles[15])
          dataNext = sixteenNibblesEnabled;
       else if (validNibbles[14])
          dataNext = fifteenNibblesEnabled;
       else if (validNibbles[13])
          dataNext = fourteenNibblesEnabled;
       else if (validNibbles[12])
          dataNext = thirteenNibblesEnabled;
       else if (validNibbles[11])
          dataNext = twelveNibblesEnabled;
       else if (validNibbles[10])
          dataNext = elevenNibblesEnabled;
       else if (validNibbles[9])
          dataNext = tenNibblesEnabled;
       else if (validNibbles[8])
          dataNext = nineNibblesEnabled;
       else if (validNibbles[7])
          dataNext = eightNibblesEnabled;
       else if (validNibbles[6])
          dataNext = sevenNibblesEnabled;
       else if (validNibbles[5])
          dataNext = sixNibblesEnabled;
       else if (validNibbles[4])
          dataNext = fiveNibblesEnabled;
       else if (validNibbles[3])
          dataNext = fourNibblesEnabled;
       else if (validNibbles[2])
          dataNext = threeNibblesEnabled;
       else if (validNibbles[1])
          dataNext = twoNibblesEnabled;
       else if (validNibbles[0])
          dataNext = oneNibbleEnabled;
   end


always @(posedge clk or negedge resetB)
  begin
     if (~resetB) begin
         number <= 64'h0;
     end
     else begin
        if (enable) begin
           number <= dataNext;
        end
     end
  end

endmodule

verilog/number_top.v
module number_top(
     //output
     number,

     //input
     clk,
     resetB,
     enable,
     numberFromBits,
);

output [63:0] number;
input clk;
input resetB;
input enable;
input [79:0] numberFromBits;

wire[15:0] nibbleChain;
wire[63:0] data;

number_brian number_brian(
   //output
   .number (number),

   //input
   .clk (clk),
   .resetB (resetB),
   .enable (enable),
   .validNibbles ({nibbleChain,1'b1}),
   .inputNumber (data)
);

number_decoder number_decoder_nibble15(
    .next_nibble_valid (nibbleChain[15]),
    .nibble(data[63:60]),

    .code(numberFromBits[79:75]),
    .this_nibble_valid(1'b1)
);

number_decoder number_decoder_nibble14(
    .next_nibble_valid (nibbleChain[14]),
    .nibble(data[59:56]),

    .code(numberFromBits[74:70]),
    .this_nibble_valid(nibbleChain[15])
);

number_decoder number_decoder_nibble13(
    .next_nibble_valid (nibbleChain[13]),
    .nibble(data[55:52]),

    .code(numberFromBits[69:65]),
    .this_nibble_valid(nibbleChain[14])
);

number_decoder number_decoder_nibble12(
    .next_nibble_valid (nibbleChain[12]),
    .nibble(data[51:48]),

    .code(numberFromBits[64:60]),
    .this_nibble_valid(nibbleChain[13])
);

number_decoder number_decoder_nibble11(
    .next_nibble_valid (nibbleChain[11]),
    .nibble(data[47:44]),

    .code(numberFromBits[59:55]),
    .this_nibble_valid(nibbleChain[12])
);

number_decoder number_decoder_nibble10(
    .next_nibble_valid (nibbleChain[10]),
    .nibble(data[43:40]),

    .code(numberFromBits[54:50]),
    .this_nibble_valid(nibbleChain[11])
);

number_decoder number_decoder_nibble09(
    .next_nibble_valid (nibbleChain[9]),
    .nibble(data[39:36]),

    .code(numberFromBits[49:45]),
    .this_nibble_valid(nibbleChain[10])
);

number_decoder number_decoder_nibble08(
    .next_nibble_valid (nibbleChain[8]),
    .nibble(data[35:32]),

    .code(numberFromBits[44:40]),
    .this_nibble_valid(nibbleChain[9])
);

number_decoder number_decoder_nibble07(
    .next_nibble_valid (nibbleChain[7]),
    .nibble(data[31:28]),

    .code(numberFromBits[39:35]),
    .this_nibble_valid(nibbleChain[8])
);

number_decoder number_decoder_nibble06(
    .next_nibble_valid (nibbleChain[6]),
    .nibble(data[27:24]),

    .code(numberFromBits[34:30]),
    .this_nibble_valid(nibbleChain[7])
);

number_decoder number_decoder_nibble05(
    .next_nibble_valid (nibbleChain[5]),
    .nibble(data[23:20]),

    .code(numberFromBits[29:25]),
    .this_nibble_valid(nibbleChain[6])
);

number_decoder number_decoder_nibble04(
    .next_nibble_valid (nibbleChain[4]),
    .nibble(data[19:16]),

    .code(numberFromBits[24:20]),
    .this_nibble_valid(nibbleChain[5])
);

number_decoder number_decoder_nibble3(
    .next_nibble_valid (nibbleChain[3]),
    .nibble(data[15:12]),

    .code(numberFromBits[19:15]),
    .this_nibble_valid(nibbleChain[4])
);

number_decoder number_decoder_nibble02(
    .next_nibble_valid (nibbleChain[2]),
    .nibble(data[11:8]),

    .code(numberFromBits[14:10]),
    .this_nibble_valid(nibbleChain[3])
);

number_decoder number_decoder_nibble01(
    .next_nibble_valid (nibbleChain[1]),
    .nibble(data[7:4]),

    .code(numberFromBits[9:5]),
    .this_nibble_valid(nibbleChain[2])
);

number_decoder number_decoder_nibble00(
    .next_nibble_valid (nibbleChain[0]),
    .nibble(data[3:0]),

    .code(numberFromBits[4:0]),
    .this_nibble_valid(nibbleChain[1])
);


endmodule

testbench/number_test.v
module number_test();

wire[63:0] number;
reg clk;
reg resetB;
reg enable;
reg[79:0] numberFromBits;

reg failed = 1'b0;

//Get some waveforms
initial begin
   $dumpfile("number.vcd");
   $dumpvars(0,number_test);
end

initial begin
   clk = 1'b0;
   failed = 1'b0;
end


//generate clk;
always
   begin
      #5 clk = ~clk;
   end

//reset sequence
initial begin
   #3 resetB = 1'b1;
   #12 resetB = 1'b0;
   #100 resetB = 1'b1;
end

//some numbers
initial begin
  numberFromBits = 80'h0;
  enable = 1'b0;
  #150
  numberFromBits = 80'h7800_0000_0000_0000_0000;
  enable = 1'b1;
  #10 enable = 1'b0;
  numberFromBits = 80'h87ff_ffff_ffff_ffff_ffff;
  #2 enable = 1'b0;
  if (number != 64'h0000_0000_0000_000f) begin
      failed = 1'b1;
  end
  #20
  numberFromBits = 80'h8fff_ffff_ffff_ffff_ffff;
  enable = 1'b1;
  #10 enable = 1'b0;
  #2 enable = 1'b0;
  if (number != 64'h1fff_ffff_ffff_ffff) begin
     failed = 1'b1;
  end
  $finish;
end

number_top number_top(
     //output
     .number (number),

     //input
     .clk (clk),
     .resetB (resetB),
     .enable (enable),
     .numberFromBits (numberFromBits)
);

endmodule

number.vcd
$date
	Tue Dec 28 13:24:52 2021
$end
$version
	Icarus Verilog
$end
$timescale
	1s
$end
$scope module number_test $end
$var wire 64 ! number [63:0] $end
$var reg 1 " clk $end
$var reg 1 # enable $end
$var reg 1 $ failed $end
$var reg 80 % numberFromBits [79:0] $end
$var reg 1 & resetB $end
$scope module number_top $end
$var wire 1 " clk $end
$var wire 1 # enable $end
$var wire 80 ' numberFromBits [79:0] $end
$var wire 1 & resetB $end
$var wire 64 ( number [63:0] $end
$var wire 16 ) nibbleChain [15:0] $end
$var wire 64 * data [63:0] $end
$scope module number_brian $end
$var wire 1 " clk $end
$var wire 1 # enable $end
$var wire 64 + inputNumber [63:0] $end
$var wire 1 & resetB $end
$var wire 64 , sixteenNibblesEnabled [63:0] $end
$var wire 17 - validNibbles [16:0] $end
$var wire 64 . twoNibblesEnabled [63:0] $end
$var wire 64 / twelveNibblesEnabled [63:0] $end
$var wire 64 0 threeNibblesEnabled [63:0] $end
$var wire 64 1 thirteenNibblesEnabled [63:0] $end
$var wire 64 2 tenNibblesEnabled [63:0] $end
$var wire 64 3 sixNibblesEnabled [63:0] $end
$var wire 64 4 sevenNibblesEnabled [63:0] $end
$var wire 64 5 oneNibbleEnabled [63:0] $end
$var wire 64 6 nineNibblesEnabled [63:0] $end
$var wire 64 7 fourteenNibblesEnabled [63:0] $end
$var wire 64 8 fourNibblesEnabled [63:0] $end
$var wire 64 9 fiveNibblesEnabled [63:0] $end
$var wire 64 : fifteenNibblesEnabled [63:0] $end
$var wire 64 ; elevenNibblesEnabled [63:0] $end
$var wire 64 < eightNibblesEnabled [63:0] $end
$var reg 64 = dataNext [63:0] $end
$var reg 64 > number [63:0] $end
$upscope $end
$scope module number_decoder_nibble00 $end
$var wire 5 ? code [4:0] $end
$var wire 1 @ next_nibble_valid $end
$var wire 4 A nibble [3:0] $end
$var wire 1 B this_nibble_valid $end
$upscope $end
$scope module number_decoder_nibble01 $end
$var wire 5 C code [4:0] $end
$var wire 1 D next_nibble_valid $end
$var wire 4 E nibble [3:0] $end
$var wire 1 F this_nibble_valid $end
$upscope $end
$scope module number_decoder_nibble02 $end
$var wire 5 G code [4:0] $end
$var wire 1 H next_nibble_valid $end
$var wire 4 I nibble [3:0] $end
$var wire 1 J this_nibble_valid $end
$upscope $end
$scope module number_decoder_nibble04 $end
$var wire 5 K code [4:0] $end
$var wire 1 L next_nibble_valid $end
$var wire 4 M nibble [3:0] $end
$var wire 1 N this_nibble_valid $end
$upscope $end
$scope module number_decoder_nibble05 $end
$var wire 5 O code [4:0] $end
$var wire 1 P next_nibble_valid $end
$var wire 4 Q nibble [3:0] $end
$var wire 1 R this_nibble_valid $end
$upscope $end
$scope module number_decoder_nibble06 $end
$var wire 5 S code [4:0] $end
$var wire 1 T next_nibble_valid $end
$var wire 4 U nibble [3:0] $end
$var wire 1 V this_nibble_valid $end
$upscope $end
$scope module number_decoder_nibble07 $end
$var wire 5 W code [4:0] $end
$var wire 1 X next_nibble_valid $end
$var wire 4 Y nibble [3:0] $end
$var wire 1 Z this_nibble_valid $end
$upscope $end
$scope module number_decoder_nibble08 $end
$var wire 5 [ code [4:0] $end
$var wire 1 \ next_nibble_valid $end
$var wire 4 ] nibble [3:0] $end
$var wire 1 ^ this_nibble_valid $end
$upscope $end
$scope module number_decoder_nibble09 $end
$var wire 5 _ code [4:0] $end
$var wire 1 ` next_nibble_valid $end
$var wire 4 a nibble [3:0] $end
$var wire 1 b this_nibble_valid $end
$upscope $end
$scope module number_decoder_nibble10 $end
$var wire 5 c code [4:0] $end
$var wire 1 d next_nibble_valid $end
$var wire 4 e nibble [3:0] $end
$var wire 1 f this_nibble_valid $end
$upscope $end
$scope module number_decoder_nibble11 $end
$var wire 5 g code [4:0] $end
$var wire 1 h next_nibble_valid $end
$var wire 4 i nibble [3:0] $end
$var wire 1 j this_nibble_valid $end
$upscope $end
$scope module number_decoder_nibble12 $end
$var wire 5 k code [4:0] $end
$var wire 1 l next_nibble_valid $end
$var wire 4 m nibble [3:0] $end
$var wire 1 n this_nibble_valid $end
$upscope $end
$scope module number_decoder_nibble13 $end
$var wire 5 o code [4:0] $end
$var wire 1 p next_nibble_valid $end
$var wire 4 q nibble [3:0] $end
$var wire 1 r this_nibble_valid $end
$upscope $end
$scope module number_decoder_nibble14 $end
$var wire 5 s code [4:0] $end
$var wire 1 t next_nibble_valid $end
$var wire 4 u nibble [3:0] $end
$var wire 1 v this_nibble_valid $end
$upscope $end
$scope module number_decoder_nibble15 $end
$var wire 5 w code [4:0] $end
$var wire 1 x next_nibble_valid $end
$var wire 4 y nibble [3:0] $end
$var wire 1 z this_nibble_valid $end
$upscope $end
$scope module number_decoder_nibble3 $end
$var wire 5 { code [4:0] $end
$var wire 1 | next_nibble_valid $end
$var wire 4 } nibble [3:0] $end
$var wire 1 ~ this_nibble_valid $end
$upscope $end
$upscope $end
$upscope $end
$enddefinitions $end
#0
$dumpvars
0~
b0 }
0|
b0 {
1z
b0 y
0x
b0 w
0v
b0 u
0t
b0 s
0r
b0 q
0p
b0 o
0n
b0 m
0l
b0 k
0j
b0 i
0h
b0 g
0f
b0 e
0d
b0 c
0b
b0 a
0`
b0 _
0^
b0 ]
0\
b0 [
0Z
b0 Y
0X
b0 W
0V
b0 U
0T
b0 S
0R
b0 Q
0P
b0 O
0N
b0 M
0L
b0 K
0J
b0 I
0H
b0 G
0F
b0 E
0D
b0 C
0B
b0 A
0@
b0 ?
bx >
b0 =
b0 <
b0 ;
b0 :
b0 9
b0 8
b0 7
b0 6
b0 5
b0 4
b0 3
b0 2
b0 1
b0 0
b0 /
b0 .
b1 -
b0 ,
b0 +
b0 *
b0 )
bx (
b0 '
x&
b0 %
0$
0#
0"
bx !
$end
#3
1&
#5
1"
#10
0"
#15
b0 !
b0 (
b0 >
1"
0&
#20
0"
#25
1"
#30
0"
#35
1"
#40
0"
#45
1"
#50
0"
#55
1"
#60
0"
#65
1"
#70
0"
#75
1"
#80
0"
#85
1"
#90
0"
#95
1"
#100
0"
#105
1"
#110
0"
#115
1"
1&
#120
0"
#125
1"
#130
0"
#135
1"
#140
0"
#145
1"
#150
b1111 =
b1111 5
b11110000 .
b111100000000 0
b1111000000000000 8
b11110000000000000000 9
b111100000000000000000000 3
b1111000000000000000000000000 4
b11110000000000000000000000000000 <
b111100000000000000000000000000000000 6
b1111000000000000000000000000000000000000 2
b11110000000000000000000000000000000000000000 ;
b111100000000000000000000000000000000000000000000 /
b1111000000000000000000000000000000000000000000000000 1
b11110000000000000000000000000000000000000000000000000000 7
b111100000000000000000000000000000000000000000000000000000000 :
b1111000000000000000000000000000000000000000000000000000000000000 ,
b1111000000000000000000000000000000000000000000000000000000000000 *
b1111000000000000000000000000000000000000000000000000000000000000 +
b1111 y
b1111 w
0"
1#
b1111000000000000000000000000000000000000000000000000000000000000000000000000000 %
b1111000000000000000000000000000000000000000000000000000000000000000000000000000 '
#155
b1111 !
b1111 (
b1111 >
1"
#160
1@
b1111 A
1B
1D
b1111 E
1F
1H
b1111 I
1J
1|
b1111 }
1~
1L
b1111 M
1N
1P
b1111 Q
1R
1T
b1111 U
1V
1X
b1111 Y
1Z
1\
b1111 ]
1^
1`
b1111 a
1b
1d
b1111 e
1f
1h
b1111 i
1j
1l
b1111 m
1n
1p
b1111 q
1r
1t
b1111 u
1v
b111111111111111111111111111111111111111111111111111111111111 =
b0 5
b1111 .
b11111111 0
b111111111111 8
b1111111111111111 9
b11111111111111111111 3
b111111111111111111111111 4
b1111111111111111111111111111 <
b11111111111111111111111111111111 6
b111111111111111111111111111111111111 2
b1111111111111111111111111111111111111111 ;
b11111111111111111111111111111111111111111111 /
b111111111111111111111111111111111111111111111111 1
b1111111111111111111111111111111111111111111111111111 7
b11111111111111111111111111111111111111111111111111111111 :
b11111111111111111 -
b1111111111111111 )
1x
b111111111111111111111111111111111111111111111111111111111111 ,
b111111111111111111111111111111111111111111111111111111111111 *
b111111111111111111111111111111111111111111111111111111111111 +
b0 y
b10000 w
b11111 s
b11111 o
b11111 k
b11111 g
b11111 c
b11111 _
b11111 [
b11111 W
b11111 S
b11111 O
b11111 K
b11111 {
b11111 G
b11111 C
b11111 ?
0"
b10000111111111111111111111111111111111111111111111111111111111111111111111111111 %
b10000111111111111111111111111111111111111111111111111111111111111111111111111111 '
0#
#165
1"
#170
0"
#175
1"
#180
0"
#182
b1111111111111111111111111111111111111111111111111111111111111 =
b1 5
b11111 .
b111111111 0
b1111111111111 8
b11111111111111111 9
b111111111111111111111 3
b1111111111111111111111111 4
b11111111111111111111111111111 <
b111111111111111111111111111111111 6
b1111111111111111111111111111111111111 2
b11111111111111111111111111111111111111111 ;
b111111111111111111111111111111111111111111111 /
b1111111111111111111111111111111111111111111111111 1
b11111111111111111111111111111111111111111111111111111 7
b111111111111111111111111111111111111111111111111111111111 :
b1111111111111111111111111111111111111111111111111111111111111 ,
b1111111111111111111111111111111111111111111111111111111111111 *
b1111111111111111111111111111111111111111111111111111111111111 +
b1 y
b10001 w
1#
b10001111111111111111111111111111111111111111111111111111111111111111111111111111 %
b10001111111111111111111111111111111111111111111111111111111111111111111111111111 '
#185
b1111111111111111111111111111111111111111111111111111111111111 !
b1111111111111111111111111111111111111111111111111111111111111 (
b1111111111111111111111111111111111111111111111111111111111111 >
1"
#190
0"
#192
0#
