verilog/ram_loader.v
module ram_loader(
   //outputs
   internalRamAddress,
   internalRamWdata,
   internalRamCEB,
   internalRamWEB,
   externalRamCEB,
   externalRamWEB,
   externalRamOEB,
   externalRamAddress,

   //inputs
   clk,
   resetB,
   externalRamReadData
);

output[9:0] internalRamAddress;
output[63:0] internalRamWdata;
output internalRamCEB;
output internalRamWEB;
output externalRamCEB;
output externalRamWEB;
output externalRamOEB;
output[18:0] externalRamAddress;

input clk;
input resetB;
input[7:0] externalRamReadData;

reg[9:0] internalRamAddress;
reg[63:0] internalRamWdata;
reg internalRamCEB;
reg internalRamWEB;
reg externalRamCEB;
reg externalRamWEB;
reg externalRamOEB;
reg[18:0] externalRamAddress;

reg[9:0] nextInternalRamAddress;
reg[63:0] nextInternalRamWdata;
reg nextInternalRamCEB;
reg nextInternalRamWEB;
reg nextExternalRamCEB;
reg nextExternalRamWEB;
reg nextExternalRamOEB;
reg[18:0] nextExternalRamAddress;


//State Machine Parameters
parameter FSM_SIZE = 4;
parameter IDLE     = 4'b0000;
parameter SEND_RD  = 4'b0001;
parameter RD0      = 4'b0010;
parameter RD1      = 4'b0011;
parameter RD2      = 4'b0100;
parameter RD3      = 4'b0101;
parameter RD4      = 4'b0110;
parameter RD5      = 4'b0111;
parameter RD6      = 4'b1000;
parameter RD7      = 4'b1001;
parameter WR       = 4'b1010;
parameter WR2RD    = 4'b1011;

reg[FSM_SIZE-1:0] state;
reg[FSM_SIZE-1:0] next_state;

always @(state or internalRamAddress or externalRamReadData or internalRamWdata
         or externalRamAddress)
  begin
     nextInternalRamAddress = internalRamAddress;
     nextInternalRamWdata = internalRamWdata;
     nextInternalRamCEB = 1'b1;
     nextInternalRamWEB = 1'b1;
     nextExternalRamCEB = 1'b1;
     nextExternalRamWEB = 1'b1;
     nextExternalRamOEB = 1'b1;
     nextExternalRamAddress = externalRamAddress;
     next_state = state;
     case(state)
        IDLE:
           begin
              next_state = SEND_RD;
              nextExternalRamCEB = 1'b0;
              nextExternalRamWEB = 1'b1;
              nextExternalRamOEB = 1'b0;
           end
        SEND_RD:
           begin
              next_state = RD0;
              nextExternalRamCEB = 1'b0;
              nextExternalRamWEB = 1'b1;
              nextExternalRamOEB = 1'b0;
              nextExternalRamAddress = externalRamAddress + 19'h00001;
           end
        RD0:
           begin
              next_state = RD1;
              nextExternalRamCEB = 1'b0;
              nextExternalRamWEB = 1'b1;
              nextExternalRamOEB = 1'b0;
              nextExternalRamAddress = externalRamAddress + 19'h00001;
              nextInternalRamWdata[63:56] = externalRamReadData[7:0];
           end
        RD1:
           begin
              next_state = RD2;
              nextExternalRamCEB = 1'b0;
              nextExternalRamWEB = 1'b1;
              nextExternalRamOEB = 1'b0;
              nextExternalRamAddress = externalRamAddress + 19'h00001;
              nextInternalRamWdata[55:48] = externalRamReadData[7:0];
           end
        RD2:
           begin
              next_state = RD3;
              nextExternalRamCEB = 1'b0;
              nextExternalRamWEB = 1'b1;
              nextExternalRamOEB = 1'b0;
              nextExternalRamAddress = externalRamAddress + 19'h00001;
              nextInternalRamWdata[47:40] = externalRamReadData[7:0];
           end
        RD3:
           begin
              next_state = RD4;
              nextExternalRamCEB = 1'b0;
              nextExternalRamWEB = 1'b1;
              nextExternalRamOEB = 1'b0;
              nextExternalRamAddress = externalRamAddress + 19'h00001;
              nextInternalRamWdata[39:32] = externalRamReadData[7:0];
           end
        RD4:
           begin
              next_state = RD5;
              nextExternalRamCEB = 1'b0;
              nextExternalRamWEB = 1'b1;
              nextExternalRamOEB = 1'b0;
              nextExternalRamAddress = externalRamAddress + 19'h00001;
              nextInternalRamWdata[31:24] = externalRamReadData[7:0];
           end
        RD5:
           begin
              next_state = RD6;
              nextExternalRamCEB = 1'b0;
              nextExternalRamWEB = 1'b1;
              nextExternalRamOEB = 1'b0;
              nextExternalRamAddress = externalRamAddress + 19'h00001;
              nextInternalRamWdata[23:16] = externalRamReadData[7:0];
           end
        RD6:
           begin
              next_state = RD7;
              nextExternalRamCEB = 1'b0;
              nextExternalRamWEB = 1'b1;
              nextExternalRamOEB = 1'b0;
              nextExternalRamAddress = externalRamAddress + 19'h00001;
              nextInternalRamWdata[15:8] = externalRamReadData[7:0];
           end
        RD7:
           begin
              next_state = WR;
              nextInternalRamWdata[7:0] = externalRamReadData[7:0];
           end
        WR:
           begin
              next_state = WR2RD;
              nextInternalRamCEB = 1'b0;
              nextInternalRamWEB = 1'b0;
           end
        WR2RD:
           begin
              next_state = RD0;
              nextInternalRamAddress = internalRamAddress + 10'h001;
              nextExternalRamCEB = 1'b0;
              nextExternalRamWEB = 1'b1;
              nextExternalRamOEB = 1'b0;
              nextExternalRamAddress = externalRamAddress + 19'h00001;
           end
     endcase
  end


always @(posedge clk or negedge resetB)
  begin
     if (~resetB) begin
        internalRamAddress <= 10'h0;
        internalRamWdata <= 64'h0;
        internalRamCEB <= 1'b1;
        internalRamWEB <= 1'b1;
        externalRamCEB <= 1'b1;
        externalRamWEB <= 1'b1;
        externalRamOEB <= 1'b1;
        externalRamAddress <= 19'h0;
        state <= IDLE;
     end
     else begin
        internalRamAddress <= nextInternalRamAddress;
        internalRamWdata <= nextInternalRamWdata;
        internalRamCEB <= nextInternalRamCEB;
        internalRamWEB <= nextInternalRamWEB;
        externalRamCEB <= nextExternalRamCEB;
        externalRamWEB <= nextExternalRamWEB;
        externalRamOEB <= nextExternalRamOEB;
        externalRamAddress <= nextExternalRamAddress;
        state <= next_state;
     end
  end

endmodule

testbench/cy62148E.v
// This is an external RAM that might be hooked up.  It is 4 MB set up in 512K words x 8 bits per word
// PDF: https://www.mouser.com/datasheet/2/100/CYPRS13582_1-2540405.pdf

module cy62148E(
    //inout
    data,

    //input
    ce_b,
    we_b,
    oe_b,
    addr
);

inout [7:0] data;

input ce_b;
input we_b;
input oe_b;
input [18:0] addr;

reg[7:0] mem[0:514288];
reg[7:0] tmp_data;


//Internal clock (running at 100 MHz)
reg clk;
initial
   begin
      clk <= 1'b0;
   end

always
   begin
      #5 clk = !clk;
   end

//Read Cycle Time: 45 ns
// Address to Data Valid: 45 ns
// Data hold from Address change: 10 ns


//Write Cycle
always @(posedge clk)
   begin
      if (!ce_b & !we_b)
         begin
            mem[addr] <= data;
         end
   end

always @(posedge clk)
   begin
       if (!ce_b & !oe_b)
          begin
             tmp_data <= mem[addr];
          end
   end

assign data = !ce_b & !oe_b & we_b ? tmp_data : 8'hz;

endmodule

testbench/ram_testbench.v
module ram_testbench();

wire [7:0] data;
wire externalRamCEB;
wire externalRamWEB;
wire externalRamOEB;
wire[18:0] externalRamAddr;

reg clk;
reg resetB;

//Get some waveforms
initial begin
   $dumpfile("ram.vcd");
   $dumpvars(0,ram_testbench);
end


initial begin
   $readmemh("testbench/memory.mem", externalRam.mem);
end

//Clock generation
initial begin
   clk = 1'b0;
   resetB = 1'b1;
end

always
  begin
     #5 clk = ~clk;
  end

//Reset Generation
initial
  begin
    #6 resetB = 1'b0;
    #25 resetB = 1'b1;
  end

//TestTime
initial
   begin
   #500 $finish;
   end

cy62148E externalRam(
    //inout
    .data(data[7:0]),

    //input
    .ce_b(externalRamCEB),
    .we_b(externalRamWEB),
    .oe_b(externalRamOEB),
    .addr(externalRamAddr)
);

ram_loader ram_loader(
   //outputs
   .internalRamAddress(),
   .internalRamWdata(),
   .internalRamCEB(),
   .internalRamWEB(),
   .externalRamCEB(externalRamCEB),
   .externalRamWEB(externalRamWEB),
   .externalRamOEB(externalRamOEB),
   .externalRamAddress(externalRamAddr),

   //inputs
   .clk(clk),
   .resetB(resetB),
   .externalRamReadData(data[7:0])
);

endmodule

ram.vcd
$date
	Wed Dec 29 13:36:08 2021
$end
$version
	Icarus Verilog
$end
$timescale
	1s
$end
$scope module ram_testbench $end
$var wire 1 ! externalRamWEB $end
$var wire 1 " externalRamOEB $end
$var wire 1 # externalRamCEB $end
$var wire 19 $ externalRamAddr [18:0] $end
$var wire 8 % data [7:0] $end
$var reg 1 & clk $end
$var reg 1 ' resetB $end
$scope module externalRam $end
$var wire 1 ! we_b $end
$var wire 1 " oe_b $end
$var wire 8 ( data [7:0] $end
$var wire 1 # ce_b $end
$var wire 19 ) addr [18:0] $end
$var reg 1 * clk $end
$var reg 8 + tmp_data [7:0] $end
$upscope $end
$scope module ram_loader $end
$var wire 1 & clk $end
$var wire 8 , externalRamReadData [7:0] $end
$var wire 1 ' resetB $end
$var reg 19 - externalRamAddress [18:0] $end
$var reg 1 # externalRamCEB $end
$var reg 1 " externalRamOEB $end
$var reg 1 ! externalRamWEB $end
$var reg 10 . internalRamAddress [9:0] $end
$var reg 1 / internalRamCEB $end
$var reg 1 0 internalRamWEB $end
$var reg 64 1 internalRamWdata [63:0] $end
$var reg 19 2 nextExternalRamAddress [18:0] $end
$var reg 1 3 nextExternalRamCEB $end
$var reg 1 4 nextExternalRamOEB $end
$var reg 1 5 nextExternalRamWEB $end
$var reg 10 6 nextInternalRamAddress [9:0] $end
$var reg 1 7 nextInternalRamCEB $end
$var reg 1 8 nextInternalRamWEB $end
$var reg 64 9 nextInternalRamWdata [63:0] $end
$var reg 4 : next_state [3:0] $end
$var reg 4 ; state [3:0] $end
$upscope $end
$upscope $end
$enddefinitions $end
#0
$dumpvars
bx ;
bx :
bx 9
x8
x7
bx 6
x5
x4
x3
bx 2
bx 1
x0
x/
bx .
bx -
bx ,
bx +
0*
bx )
bx (
1'
0&
bx %
bx $
x#
x"
x!
$end
#5
1&
1*
#6
bz %
bz (
bz ,
b1 :
b0 2
04
15
03
18
17
b0 9
b0 6
b0 ;
b0 $
b0 )
b0 -
1"
1!
1#
10
1/
b0 1
b0 .
0'
#10
0&
0*
#15
1&
1*
#20
0&
0*
#25
1&
1*
#30
0&
0*
#31
1'
#35
bx %
bx (
bx ,
b1 2
b10 :
04
03
b1 ;
0"
0#
1&
1*
#40
0&
0*
#45
b110000000000000000000000000000000000000000000000000000000000000 9
b10 2
b11 :
04
03
b1100000 %
b1100000 (
b1100000 ,
b10 ;
b1 $
b1 )
b1 -
b1100000 +
1&
1*
#50
0&
0*
#55
b110000001010001000000000000000000000000000000000000000000000000 9
b11 2
b100 :
04
03
b1010001 %
b1010001 (
b1010001 ,
b11 ;
b10 $
b10 )
b10 -
b110000000000000000000000000000000000000000000000000000000000000 1
b1010001 +
1&
1*
#60
0&
0*
#65
b110000001010001011000110000000000000000000000000000000000000000 9
b100 2
b101 :
04
03
b1100011 %
b1100011 (
b1100011 ,
b100 ;
b11 $
b11 )
b11 -
b110000001010001000000000000000000000000000000000000000000000000 1
b1100011 +
1&
1*
#70
0&
0*
#75
b110000001010001011000111001000000000000000000000000000000000000 9
b101 2
b110 :
04
03
b10010000 %
b10010000 (
b10010000 ,
b101 ;
b100 $
b100 )
b100 -
b110000001010001011000110000000000000000000000000000000000000000 1
b10010000 +
1&
1*
#80
0&
0*
#85
b110000001010001011000111001000000000101000000000000000000000000 9
b110 2
b111 :
04
03
b101 %
b101 (
b101 ,
b110 ;
b101 $
b101 )
b101 -
b110000001010001011000111001000000000000000000000000000000000000 1
b101 +
1&
1*
#90
0&
0*
#95
b110000001010001011000111001000000000101101101010000000000000000 9
b111 2
b1000 :
04
03
b10110101 %
b10110101 (
b10110101 ,
b111 ;
b110 $
b110 )
b110 -
b110000001010001011000111001000000000101000000000000000000000000 1
b10110101 +
1&
1*
#100
0&
0*
#105
b110000001010001011000111001000000000101101101010110000000000000 9
b1000 2
b1001 :
04
03
b1100000 %
b1100000 (
b1100000 ,
b1000 ;
b111 $
b111 )
b111 -
b110000001010001011000111001000000000101101101010000000000000000 1
b1100000 +
1&
1*
#110
0&
0*
#115
b110000001010001011000111001000000000101101101010110000000001000 9
b1010 :
14
13
b1000 %
b1000 (
b1000 ,
b1001 ;
b1000 $
b1000 )
b1000 -
b110000001010001011000111001000000000101101101010110000000000000 1
b1000 +
1&
1*
#120
0&
0*
#125
08
07
b1011 :
bz %
bz (
bz ,
b1010 ;
1"
1#
b110000001010001011000111001000000000101101101010110000000001000 1
b11000001 +
1&
1*
#130
0&
0*
#135
b1001 2
04
03
b1 6
b10 :
18
17
b1011 ;
00
0/
1&
1*
#140
0&
0*
#145
b11000001 %
b11000001 (
b11000001 ,
b1100000101010001011000111001000000000101101101010110000000001000 9
b1010 2
b11 :
04
03
b10 ;
b1001 $
b1001 )
b1001 -
0"
0#
10
1/
b1 .
1&
1*
#150
0&
0*
#155
b1100000111011001011000111001000000000101101101010110000000001000 9
b1011 2
b100 :
04
03
b11011001 %
b11011001 (
b11011001 ,
b11 ;
b1010 $
b1010 )
b1010 -
b1100000101010001011000111001000000000101101101010110000000001000 1
b11011001 +
1&
1*
#160
0&
0*
#165
b1100000111011001101110111001000000000101101101010110000000001000 9
b1100 2
b101 :
04
03
b10111011 %
b10111011 (
b10111011 ,
b100 ;
b1011 $
b1011 )
b1011 -
b1100000111011001011000111001000000000101101101010110000000001000 1
b10111011 +
1&
1*
#170
0&
0*
#175
b1100000111011001101110110011110000000101101101010110000000001000 9
b1101 2
b110 :
04
03
b111100 %
b111100 (
b111100 ,
b101 ;
b1100 $
b1100 )
b1100 -
b1100000111011001101110111001000000000101101101010110000000001000 1
b111100 +
1&
1*
#180
0&
0*
#185
b1100000111011001101110110011110011001001101101010110000000001000 9
b1110 2
b111 :
04
03
b11001001 %
b11001001 (
b11001001 ,
b110 ;
b1101 $
b1101 )
b1101 -
b1100000111011001101110110011110000000101101101010110000000001000 1
b11001001 +
1&
1*
#190
0&
0*
#195
b1100000111011001101110110011110011001001110110100110000000001000 9
b1111 2
b1000 :
04
03
b11011010 %
b11011010 (
b11011010 ,
b111 ;
b1110 $
b1110 )
b1110 -
b1100000111011001101110110011110011001001101101010110000000001000 1
b11011010 +
1&
1*
#200
0&
0*
#205
b1100000111011001101110110011110011001001110110101101010100001000 9
b10000 2
b1001 :
04
03
b11010101 %
b11010101 (
b11010101 ,
b1000 ;
b1111 $
b1111 )
b1111 -
b1100000111011001101110110011110011001001110110100110000000001000 1
b11010101 +
1&
1*
#210
0&
0*
#215
b1100000111011001101110110011110011001001110110101101010110111110 9
b1010 :
14
13
b10111110 %
b10111110 (
b10111110 ,
b1001 ;
b10000 $
b10000 )
b10000 -
b1100000111011001101110110011110011001001110110101101010100001000 1
b10111110 +
1&
1*
#220
0&
0*
#225
08
07
b1011 :
bz %
bz (
bz ,
b1010 ;
1"
1#
b1100000111011001101110110011110011001001110110101101010110111110 1
b10010111 +
1&
1*
#230
0&
0*
#235
b10001 2
04
03
b10 6
b10 :
18
17
b1011 ;
00
0/
1&
1*
#240
0&
0*
#245
b10010111 %
b10010111 (
b10010111 ,
b1001011111011001101110110011110011001001110110101101010110111110 9
b10010 2
b11 :
04
03
b10 ;
b10001 $
b10001 )
b10001 -
0"
0#
10
1/
b10 .
1&
1*
#250
0&
0*
#255
b1001011110100100101110110011110011001001110110101101010110111110 9
b10011 2
b100 :
04
03
b10100100 %
b10100100 (
b10100100 ,
b11 ;
b10010 $
b10010 )
b10010 -
b1001011111011001101110110011110011001001110110101101010110111110 1
b10100100 +
1&
1*
#260
0&
0*
#265
b1001011110100100101010010011110011001001110110101101010110111110 9
b10100 2
b101 :
04
03
b10101001 %
b10101001 (
b10101001 ,
b100 ;
b10011 $
b10011 )
b10011 -
b1001011110100100101110110011110011001001110110101101010110111110 1
b10101001 +
1&
1*
#270
0&
0*
#275
b1001011110100100101010010001000011001001110110101101010110111110 9
b10101 2
b110 :
04
03
b10000 %
b10000 (
b10000 ,
b101 ;
b10100 $
b10100 )
b10100 -
b1001011110100100101010010011110011001001110110101101010110111110 1
b10000 +
1&
1*
#280
0&
0*
#285
b1001011110100100101010010001000001000111110110101101010110111110 9
b10110 2
b111 :
04
03
b1000111 %
b1000111 (
b1000111 ,
b110 ;
b10101 $
b10101 )
b10101 -
b1001011110100100101010010001000011001001110110101101010110111110 1
b1000111 +
1&
1*
#290
0&
0*
#295
b1001011110100100101010010001000001000111000000001101010110111110 9
b10111 2
b1000 :
04
03
b0 %
b0 (
b0 ,
b111 ;
b10110 $
b10110 )
b10110 -
b1001011110100100101010010001000001000111110110101101010110111110 1
b0 +
1&
1*
#300
0&
0*
#305
b1001011110100100101010010001000001000111000000001010111010111110 9
b11000 2
b1001 :
04
03
b10101110 %
b10101110 (
b10101110 ,
b1000 ;
b10111 $
b10111 )
b10111 -
b1001011110100100101010010001000001000111000000001101010110111110 1
b10101110 +
1&
1*
#310
0&
0*
#315
b1001011110100100101010010001000001000111000000001010111001110110 9
b1010 :
14
13
b1110110 %
b1110110 (
b1110110 ,
b1001 ;
b11000 $
b11000 )
b11000 -
b1001011110100100101010010001000001000111000000001010111010111110 1
b1110110 +
1&
1*
#320
0&
0*
#325
08
07
b1011 :
bz %
bz (
bz ,
b1010 ;
1"
1#
b1001011110100100101010010001000001000111000000001010111001110110 1
b11100110 +
1&
1*
#330
0&
0*
#335
b11001 2
04
03
b11 6
b10 :
18
17
b1011 ;
00
0/
1&
1*
#340
0&
0*
#345
b11100110 %
b11100110 (
b11100110 ,
b1110011010100100101010010001000001000111000000001010111001110110 9
b11010 2
b11 :
04
03
b10 ;
b11001 $
b11001 )
b11001 -
0"
0#
10
1/
b11 .
1&
1*
#350
0&
0*
#355
b1110011001110010101010010001000001000111000000001010111001110110 9
b11011 2
b100 :
04
03
b1110010 %
b1110010 (
b1110010 ,
b11 ;
b11010 $
b11010 )
b11010 -
b1110011010100100101010010001000001000111000000001010111001110110 1
b1110010 +
1&
1*
#360
0&
0*
#365
b1110011001110010110111000001000001000111000000001010111001110110 9
b11100 2
b101 :
04
03
b11011100 %
b11011100 (
b11011100 ,
b100 ;
b11011 $
b11011 )
b11011 -
b1110011001110010101010010001000001000111000000001010111001110110 1
b11011100 +
1&
1*
#370
0&
0*
#375
b1110011001110010110111001001010101000111000000001010111001110110 9
b11101 2
b110 :
04
03
b10010101 %
b10010101 (
b10010101 ,
b101 ;
b11100 $
b11100 )
b11100 -
b1110011001110010110111000001000001000111000000001010111001110110 1
b10010101 +
1&
1*
#380
0&
0*
#385
b1110011001110010110111001001010110101010000000001010111001110110 9
b11110 2
b111 :
04
03
b10101010 %
b10101010 (
b10101010 ,
b110 ;
b11101 $
b11101 )
b11101 -
b1110011001110010110111001001010101000111000000001010111001110110 1
b10101010 +
1&
1*
#390
0&
0*
#395
b1110011001110010110111001001010110101010111010011010111001110110 9
b11111 2
b1000 :
04
03
b11101001 %
b11101001 (
b11101001 ,
b111 ;
b11110 $
b11110 )
b11110 -
b1110011001110010110111001001010110101010000000001010111001110110 1
b11101001 +
1&
1*
#400
0&
0*
#405
b1110011001110010110111001001010110101010111010010001010001110110 9
b100000 2
b1001 :
04
03
b10100 %
b10100 (
b10100 ,
b1000 ;
b11111 $
b11111 )
b11111 -
b1110011001110010110111001001010110101010111010011010111001110110 1
b10100 +
1&
1*
#410
0&
0*
#415
b1110011001110010110111001001010110101010111010010001010000100101 9
b1010 :
14
13
b100101 %
b100101 (
b100101 ,
b1001 ;
b100000 $
b100000 )
b100000 -
b1110011001110010110111001001010110101010111010010001010001110110 1
b100101 +
1&
1*
#420
0&
0*
#425
08
07
b1011 :
bz %
bz (
bz ,
b1010 ;
1"
1#
b1110011001110010110111001001010110101010111010010001010000100101 1
b11101111 +
1&
1*
#430
0&
0*
#435
b100001 2
04
03
b100 6
b10 :
18
17
b1011 ;
00
0/
1&
1*
#440
0&
0*
#445
b11101111 %
b11101111 (
b11101111 ,
b1110111101110010110111001001010110101010111010010001010000100101 9
b100010 2
b11 :
04
03
b10 ;
b100001 $
b100001 )
b100001 -
0"
0#
10
1/
b100 .
1&
1*
#450
0&
0*
#455
b1110111101101010110111001001010110101010111010010001010000100101 9
b100011 2
b100 :
04
03
b1101010 %
b1101010 (
b1101010 ,
b11 ;
b100010 $
b100010 )
b100010 -
b1110111101110010110111001001010110101010111010010001010000100101 1
b1101010 +
1&
1*
#460
0&
0*
#465
b1110111101101010110110001001010110101010111010010001010000100101 9
b100100 2
b101 :
04
03
b11011000 %
b11011000 (
b11011000 ,
b100 ;
b100011 $
b100011 )
b100011 -
b1110111101101010110111001001010110101010111010010001010000100101 1
b11011000 +
1&
1*
#470
0&
0*
#475
b1110111101101010110110001011101010101010111010010001010000100101 9
b100101 2
b110 :
04
03
b10111010 %
b10111010 (
b10111010 ,
b101 ;
b100100 $
b100100 )
b100100 -
b1110111101101010110110001001010110101010111010010001010000100101 1
b10111010 +
1&
1*
#480
0&
0*
#485
b1110111101101010110110001011101001010101111010010001010000100101 9
b100110 2
b111 :
04
03
b1010101 %
b1010101 (
b1010101 ,
b110 ;
b100101 $
b100101 )
b100101 -
b1110111101101010110110001011101010101010111010010001010000100101 1
b1010101 +
1&
1*
#490
0&
0*
#495
b1110111101101010110110001011101001010101100100010001010000100101 9
b100111 2
b1000 :
04
03
b10010001 %
b10010001 (
b10010001 ,
b111 ;
b100110 $
b100110 )
b100110 -
b1110111101101010110110001011101001010101111010010001010000100101 1
b10010001 +
1&
1*
