testbench/apb_driver.v
module apb_driver(
   //outputs
   paddr,
   pwrite,
   psel,
   penable,
   pwdata,

   //inputs
   clk,
   prdata
);

output [7:0]  paddr;
output        pwrite;
output        psel;
output        penable;
output [31:0] pwdata;

input         clk;
input[31:0]   prdata;

reg [7:0]   paddr;
reg         pwrite;
reg         psel;
reg         penable;
reg [31:0]  pwdata;


task write;
  input [7:0] addr;
  input [31:0] data;
  begin
    @(negedge clk);
    psel = 1'b1;
    pwrite = 1'b1;
    paddr = addr;
    pwdata = data;
    penable = 0;

    // this is the ENABLE state where the penable is asserted
    @(negedge clk);
    penable = 1;
  end
endtask


  // read ()
  //
  // Simple read method used in the unit tests.
  // Includes options for back-to-back reads.
  //
task read;
  input[7:0] addr;
  output[31:0] data;
  begin
    @(negedge clk);
    psel = 1;
    paddr = addr;
    penable = 0;
    pwrite = 0;

    // this is the ENABLE state where the penable is asserted
    @(negedge clk);
    penable = 1;

    // the prdata should be flopped after the subsequent posedge
    @(posedge clk);
    #1 data = prdata;
  end
endtask

  // idle ()
  //
  // Clear the all the inputs to the uut (i.e. move to the IDLE state)
task idle();
  begin
    @(negedge clk);
    psel = 0;
    penable = 0;
    pwrite = 0;
    paddr = 0;
    pwdata = 0;
  end
endtask

endmodule

testbench/reset_generator.v
module reset_generator(
   //output
   resetB,

   //inputs
   clk
);

output resetB;

input  clk;

reg resetB;

reg [4:0] counter;
initial begin
   counter = 5'ha;
   @(negedge clk);
   resetB = 1'b1;
   @(negedge clk);
   resetB = 1'b0;
   while(counter > 0)
     begin
        @(posedge clk)
        counter = counter - 1;
     end
   @(negedge clk);
   resetB = 1'b1;
end

endmodule

testbench/clk_generator.v
module clk_generator (
   clk
);

output clk;

reg clk;

//clk generator
initial begin
  clk = 0;
  forever begin
     #5 clk = ~clk;
  end
end

endmodule

testbench/mem1024x32.v
module mem1024x32(
   //output
   rdata,

   //input
   clk,
   ceb,
   web,
   addr,
   wdata
);

output[31:0] rdata;

input clk;
input ceb;
input web;
input[9:0] addr;
input[31:0] wdata;

initial begin
  $readmemh("memory.mem", mem);
end

reg[31:0] mem[0:1023];
reg[31:0] rdata;

//Write Cycle
always @(posedge clk)
   begin
      if (!ceb & !web)
         begin
            mem[addr] <= wdata;
         end
   end

always @(posedge clk)
   begin
       if (!ceb & web)
          begin
             rdata <= mem[addr];
          end
   end

endmodule

verilog/imem_controller.v
module imem_controller(
    //outputs
    // -- Instruction Memory Access (Read Only)
    imem_ceb,
    imem_web,
    imem_addr,

    // -- Status to be sent to bits_fsm
    done_reading_memory,
    instruction_word,
    instruction_valid_bytes,

    //inputs
    // -- System Inputs
    clk,
    resetB,

    //--Instruction Memory Read Data
    imem_rdata,

    //--Control bits from Bits_reg
    start,
    expectedBytes
);

output        imem_ceb;
output        imem_web;
output[9:0]   imem_addr;

output        done_reading_memory;
output[127:0] instruction_word;
output[15:0]  instruction_valid_bytes;

input         clk;
input         resetB;

input[31:0]   imem_rdata;

input         start;
input[15:0]   expectedBytes;


reg[127:0]   instruction_word;
reg[16:0]    byteCounter;
reg[3:0]     state;
reg[127:0]   instruction_word_next;
reg[3:0]     state_next;
reg[16:0]    byteCounter_next;

reg          imem_ceb;
reg          imem_web;
reg[9:0]     imem_addr;
reg          imem_ceb_next;
reg          imem_web_next;
reg[9:0]     imem_addr_next;
reg          done_reading_memory;
reg          done_reading_memory_next;

parameter IDLE       = 4'b0000;
parameter READ_WAIT  = 4'b0001;
parameter READ_INST0 = 4'b0010;
parameter READ_INST1 = 4'b0011;
parameter READ_INST2 = 4'b0100;
parameter READ_INST3 = 4'b0101;
parameter FINISH_RD  = 4'b0110;

parameter DONE     = 4'b1111;

always @(state or start or expectedBytes or byteCounter or imem_addr or instruction_word)
begin
  state_next = state;
  imem_ceb_next = 1'b1;
  imem_web_next = 1'b1;
  imem_addr_next = imem_addr;
  byteCounter_next = byteCounter;
  instruction_word_next = instruction_word;
  done_reading_memory_next = 1'b0;
  case (state)
     IDLE:
       begin
          if (start) begin
             state_next = READ_WAIT;
             imem_ceb_next = 1'b0;
             imem_web_next = 1'b1;
             imem_addr_next = imem_addr;
             byteCounter_next = byteCounter + 16'h0004;
          end
       end
     READ_WAIT:
       begin
          state_next = READ_INST0;
          if (byteCounter <= expectedBytes) begin
             state_next = READ_INST0;
             imem_ceb_next = 1'b0;
             imem_web_next = 1'b1;
             imem_addr_next = imem_addr + 10'h1;
             byteCounter_next = byteCounter + 16'h0004;
          end
       end
     READ_INST0:
       begin
          if (byteCounter <= expectedBytes) begin
             state_next = READ_INST1;
             imem_ceb_next = 1'b0;
             imem_web_next = 1'b1;
             imem_addr_next = imem_addr + 10'h1;
             byteCounter_next = byteCounter + 16'h0004;
          end
          else begin
             state_next = DONE;
             done_reading_memory_next = 1'b1;
          end
          instruction_word_next[127:96] = imem_rdata;
       end
     READ_INST1:
       begin
          if (byteCounter <= expectedBytes) begin
             state_next = READ_INST2;
             imem_ceb_next = 1'b0;
             imem_web_next = 1'b1;
             imem_addr_next = imem_addr + 10'h1;
             byteCounter_next = byteCounter + 16'h0004;
          end
          else begin
             state_next = DONE;
             done_reading_memory_next = 1'b1;
          end
          instruction_word_next[95:64] = imem_rdata;
       end
     READ_INST2:
       begin
          if (byteCounter <= expectedBytes) begin
             state_next = READ_INST3;
             imem_ceb_next = 1'b0;
             imem_web_next = 1'b1;
             imem_addr_next = imem_addr + 10'h1;
             byteCounter_next = byteCounter + 16'h0004;
          end
          else begin
             state_next = DONE;
             done_reading_memory_next = 1'b1;
          end
          instruction_word_next[63:32] = imem_rdata;
       end
     READ_INST3:
       begin
          if (byteCounter <= expectedBytes) begin
             state_next = FINISH_RD;
          end
          else begin
             state_next = DONE;
             done_reading_memory_next = 1'b1;
          end
          instruction_word_next[31:0] = imem_rdata;
       end
     FINISH_RD:
       begin
          if (byteCounter <= expectedBytes) begin
             state_next = READ_INST1;
             imem_ceb_next = 1'b0;
             imem_web_next = 1'b1;
             imem_addr_next = imem_addr + 10'h1;
          end
          else begin
             state_next = DONE;
             done_reading_memory_next = 1'b1;
          end
          instruction_word_next[127:96] = imem_rdata;
       end
     endcase

end

always @(posedge clk or negedge resetB)
begin
  if (~resetB)
    begin
       state <= IDLE;
       byteCounter <= 16'h0;
       imem_ceb <= 1'b1;
       imem_web <= 1'b1;
       imem_addr <= 10'h0;
       instruction_word <= 128'h0;
       done_reading_memory <= 1'b0;
    end
    else begin
       state <= state_next;
       byteCounter <= byteCounter_next;
       imem_ceb <= imem_ceb_next;
       imem_web <= imem_web_next;
       imem_addr <= imem_addr_next;
       instruction_word <= instruction_word_next;
       done_reading_memory <= done_reading_memory_next;
    end
end

endmodule

verilog/bits_regs.v
// Uses AMBA 3 APB Signals to connect to.

module bits_regs(
    //outputs
    // -- AMBA Peripheral Bus Signals
    pready,
    prdata,
    pslverr,

    // -- Signals to send to BITS Core
    expected_bytes,
    start,

    //inputs
    // -- System Inputs
    clk,
    resetB,

    // -- AMBA Peripheral Bus Signals
    paddr,
    psel,
    penable,
    pwrite,
    pwdata,

    // -- Signals from BITS Core
    done,
    bits_value,
    bits_enable,
    version_sum,
);

output       pready;
output[31:0] prdata;
output       pslverr;

output[15:0] expected_bytes;
output       start;

input        clk;
input        resetB;
input[7:2]   paddr;
input        psel;
input        penable;
input        pwrite;
input[31:0]  pwdata;

input        done;
input[63:0]  bits_value;
input        bits_enable;
input[15:0]  version_sum;

reg          start;
reg[15:0]    expected_bytes;
reg          done_latched;
reg[15:0]    version_sum_latched;
reg[63:0]    bits_value_latched;
reg[31:0]    prdata;

wire write_cycle;
wire read_cycle;
wire pready;
wire pslverr;

assign pready = 1'b1;  //Will always complete in one cycle.
assign pslverr = 1'b0;  // No errors from this peripheral.

assign write_cycle = psel & penable & pwrite;
assign read_cycle = psel & penable & ~pwrite;

always @(read_cycle or done or version_sum_latched or bits_value_latched or paddr)
  begin
     prdata = 31'h0;
     case(paddr)
        6'h00 :
           begin
             prdata = {23'h0,done,8'h0};
           end
        6'h01 :
           begin
             prdata = {16'h0,expected_bytes};
           end
        6'h02 :
           begin
              prdata = {16'h0,version_sum_latched};
           end
        6'h04 :
           begin
              prdata = bits_value_latched[63:32];
           end
        6'h05 :
           begin
              prdata = bits_value_latched[31:0];
           end
     endcase
  end

always @(posedge clk or negedge resetB)
  begin
     if (~resetB)
       begin
          start <= 1'b0;
          expected_bytes <= 16'h0;
       end
     else
       begin
         if (pwrite & (paddr[7:2] == 6'h00))
           begin
              start <= pwdata[0];
           end
         else if (pwrite & (paddr[7:2] == 6'h01))
           begin
              expected_bytes <= pwdata[15:0];
           end
         else
           begin
             start <= 1'b0;
           end
       end
  end

always @(posedge clk or negedge resetB)
  begin
     if (~resetB)
       begin
          done_latched <= 1'b0;
          version_sum_latched <= 16'h0;
          bits_value_latched <= 64'h0;
       end
     else
       begin
         if (start)
           begin
             done_latched <= 1'b0;
             version_sum_latched <= 16'h0;
             bits_value_latched = 64'h0;
           end
         else if (done)
           begin
             done_latched <= 1'b1;
             version_sum_latched <= version_sum;
             bits_value_latched <= bits_value;
           end
       end
  end

endmodule

verilog/bits_top.v
module bits_top(
   //outputs
   // --AMBA Peripheral Bus Signals
   pready,
   prdata,
   pslverr,
   // -- Instruction Memory
   imem_ceb,
   imem_web,
   imem_addr,


   //inputs
   // --System inputs
   clk,
   resetB,

   // -- AMBA Peripheral Bus Signals
   paddr,
   psel,
   penable,
   pwrite,
   pwdata,

   //--Instruction Memory
  imem_rdata,



);

output       pready;
output[31:0] prdata;
output       pslverr;

output       imem_ceb;
output       imem_web;
output[9:0]  imem_addr;

input        clk;
input        resetB;
input[7:2]   paddr;
input        psel;
input        penable;
input        pwrite;
input[31:0]  pwdata;

input[31:0]  imem_rdata;

wire       start;
wire[15:0] expectedBytes;

bits_regs bits_regs(
    //outputs
    // -- AMBA Peripheral Bus Signals
    .pready (),
    .prdata (prdata),
    .pslverr(),

    // -- Signals to send to BITS Core
    .expected_bytes(expectedBytes),
    .start(start),

    //inputs
    // -- System Inputs
    .clk (clk),
    .resetB (resetB),

    // -- AMBA Peripheral Bus Signals
    .paddr (paddr[7:2]),
    .psel (psel),
    .penable (penable),
    .pwrite (pwrite),
    .pwdata (pwdata),

    // -- Signals from BITS Core
    .done (1'b0),
    .bits_value (64'h0),
    .bits_enable (1'b0),
    .version_sum(16'h0)
);

imem_controller imem_controller(
    //outputs
    // -- Instruction Memory Access (Read Only)
    .imem_ceb (imem_ceb),
    .imem_web (imem_web),
    .imem_addr (imem_addr),

    // -- Status to be sent to bits_regs
    .done_reading_memory (),
    .instruction_word (),
    .instruction_valid_bytes(),

    //inputs
    // -- System Inputs
    .clk (clk),
    .resetB (resetB),

    //--Instruction Memory Read Data
    .imem_rdata (imem_rdata),

    //--Control bits from Bits_reg
    .start  (start),
    .expectedBytes (expectedBytes)
);


endmodule

testbench/bits_testbench.v
`timescale 1ns/1ns

module bits_testbench();

wire clk;
wire resetB;
wire [7:0]   paddr;
wire         pwrite;
wire         psel;
wire         penable;
wire [31:0]  pwdata;
wire [31:0] prdata;

wire imem_ceb;
wire imem_web;
wire[9:0] imem_addr;
wire[31:0] imem_rdata;

bits_top bits_top(
    //outputs
    // -- AMBA Peripheral Bus Signals
    .pready (),
    .prdata (prdata),
    .pslverr(),

    // -- Instruction Memory
    .imem_ceb (imem_ceb),
    .imem_web (imem_web),
    .imem_addr (imem_addr),

    //inputs
    // -- System Inputs
    .clk (clk),
    .resetB (resetB),

    // -- AMBA Peripheral Bus Signals
    .paddr (paddr[7:2]),
    .psel (psel),
    .penable (penable),
    .pwrite (pwrite),
    .pwdata (pwdata),
    // -- Instruction Memory
    .imem_rdata (imem_rdata)
);

mem1024x32 imem(
   //output
   .rdata (imem_rdata),

   //input
   .clk (clk),
   .ceb (imem_ceb),
   .web (imem_web),
   .addr (imem_addr),
   .wdata (32'h0)
);

clk_generator clk_generator(
   .clk (clk)
);

reset_generator reset_generator(
   .resetB(resetB),
   .clk(clk)
);

apb_driver apb_driver(
   //outputs
   .paddr (paddr),
   .pwrite (pwrite),
   .psel  (psel),
   .penable (penable),
   .pwdata (pwdata),

   //inputs
   .clk (clk),
   .prdata (prdata)
);

wire[31:0] expectedBytes;
assign expectedBytes = imem.mem[1023];

initial begin
   @(negedge resetB);
   @(posedge resetB);
   @(negedge clk);
   apb_driver.idle();
   @(negedge clk);
   apb_driver.write(8'h04,expectedBytes);
   apb_driver.idle();
   @(negedge clk);
   apb_driver.write(8'h00,32'h01);
   apb_driver.idle();
   #500 $finish;

end


endmodule

tests/simpleNumberPacket/dump.vcd
$date
	Thu Dec 30 21:32:43 2021
$end
$version
	Icarus Verilog
$end
$timescale
	1ns
$end
$scope module bits_testbench $end
$var wire 32 ! expectedBytes [31:0] $end
$var wire 1 " resetB $end
$var wire 1 # pwrite $end
$var wire 32 $ pwdata [31:0] $end
$var wire 1 % psel $end
$var wire 32 & prdata [31:0] $end
$var wire 1 ' penable $end
$var wire 8 ( paddr [7:0] $end
$var wire 1 ) imem_web $end
$var wire 32 * imem_rdata [31:0] $end
$var wire 1 + imem_ceb $end
$var wire 10 , imem_addr [9:0] $end
$var wire 1 - clk $end
$scope module apb_driver $end
$var wire 32 . prdata [31:0] $end
$var wire 1 - clk $end
$var reg 8 / paddr [7:0] $end
$var reg 1 ' penable $end
$var reg 1 % psel $end
$var reg 32 0 pwdata [31:0] $end
$var reg 1 # pwrite $end
$scope task idle $end
$upscope $end
$scope task read $end
$var reg 8 1 addr [7:0] $end
$var reg 32 2 data [31:0] $end
$upscope $end
$scope task write $end
$var reg 8 3 addr [7:0] $end
$var reg 32 4 data [31:0] $end
$upscope $end
$upscope $end
$scope module bits_top $end
$var wire 6 5 paddr [7:2] $end
$var wire 1 ' penable $end
$var wire 1 6 pready $end
$var wire 1 % psel $end
$var wire 1 7 pslverr $end
$var wire 32 8 pwdata [31:0] $end
$var wire 1 # pwrite $end
$var wire 1 9 start $end
$var wire 1 " resetB $end
$var wire 32 : prdata [31:0] $end
$var wire 1 ) imem_web $end
$var wire 32 ; imem_rdata [31:0] $end
$var wire 1 + imem_ceb $end
$var wire 10 < imem_addr [9:0] $end
$var wire 16 = expectedBytes [15:0] $end
$var wire 1 - clk $end
$scope module bits_regs $end
$var wire 1 > bits_enable $end
$var wire 64 ? bits_value [63:0] $end
$var wire 1 @ done $end
$var wire 6 A paddr [7:2] $end
$var wire 1 ' penable $end
$var wire 1 B pready $end
$var wire 1 % psel $end
$var wire 1 C pslverr $end
$var wire 32 D pwdata [31:0] $end
$var wire 1 # pwrite $end
$var wire 1 E read_cycle $end
$var wire 16 F version_sum [15:0] $end
$var wire 1 G write_cycle $end
$var wire 1 " resetB $end
$var wire 1 - clk $end
$var reg 64 H bits_value_latched [63:0] $end
$var reg 1 I done_latched $end
$var reg 16 J expected_bytes [15:0] $end
$var reg 32 K prdata [31:0] $end
$var reg 1 9 start $end
$var reg 16 L version_sum_latched [15:0] $end
$upscope $end
$scope module imem_controller $end
$var wire 16 M expectedBytes [15:0] $end
$var wire 16 N instruction_valid_bytes [15:0] $end
$var wire 1 9 start $end
$var wire 1 " resetB $end
$var wire 32 O imem_rdata [31:0] $end
$var wire 1 - clk $end
$var reg 17 P byteCounter [16:0] $end
$var reg 17 Q byteCounter_next [16:0] $end
$var reg 1 R done_reading_memory $end
$var reg 1 S done_reading_memory_next $end
$var reg 10 T imem_addr [9:0] $end
$var reg 10 U imem_addr_next [9:0] $end
$var reg 1 + imem_ceb $end
$var reg 1 V imem_ceb_next $end
$var reg 1 ) imem_web $end
$var reg 1 W imem_web_next $end
$var reg 128 X instruction_word [127:0] $end
$var reg 128 Y instruction_word_next [127:0] $end
$var reg 4 Z state [3:0] $end
$var reg 4 [ state_next [3:0] $end
$upscope $end
$upscope $end
$scope module clk_generator $end
$var reg 1 - clk $end
$upscope $end
$scope module imem $end
$var wire 10 \ addr [9:0] $end
$var wire 1 + ceb $end
$var wire 1 - clk $end
$var wire 32 ] wdata [31:0] $end
$var wire 1 ) web $end
$var reg 32 ^ rdata [31:0] $end
$upscope $end
$scope module reset_generator $end
$var wire 1 - clk $end
$var reg 5 _ counter [4:0] $end
$var reg 1 " resetB $end
$upscope $end
$upscope $end
$enddefinitions $end
#0
$dumpvars
b1010 _
bx ^
b0 ]
bx \
bx [
bx Z
bx Y
bx X
xW
xV
bx U
bx T
xS
xR
bx Q
bx P
bx O
bz N
bx M
bx L
b0 K
bx J
xI
bx H
xG
b0 F
xE
bx D
0C
1B
bx A
0@
b0 ?
0>
bx =
bx <
bx ;
b0 :
x9
bx 8
z7
z6
bx 5
bx 4
bx 3
bx 2
bx 1
bx 0
bx /
b0 .
0-
bx ,
x+
bx *
x)
bx (
x'
b0 &
x%
bx $
x#
x"
b11 !
$end
#5
0S
1W
1V
09
1-
#10
1"
0-
#15
0R
1)
1+
1-
#20
b0 Y
b0 Q
b0 U
b0 [
b0 =
b0 J
b0 M
b0 H
b0 L
0I
b0 X
b0 ,
b0 <
b0 T
b0 \
b0 P
b0 Z
0"
0-
#25
b1001 _
1-
#30
0-
#35
b1000 _
1-
#40
0-
#45
b111 _
1-
#50
0-
#55
b110 _
1-
#60
0-
#65
b101 _
1-
#70
0-
#75
b100 _
1-
#80
0-
#85
b11 _
1-
#90
0-
#95
b10 _
1-
#100
0-
#105
b1 _
1-
#110
0-
#115
b0 _
1-
#120
1"
0-
#125
1-
#130
0-
#135
1-
#140
0E
b0 5
b0 A
0G
b0 $
b0 0
b0 8
b0 D
b0 (
b0 /
0#
0'
0%
0-
#145
1-
#150
b11 4
b100 3
0-
#155
1-
#160
b1 5
b1 A
b11 $
b11 0
b11 8
b11 D
b100 (
b100 /
1#
1%
0-
#165
b11 =
b11 J
b11 M
1-
#170
1G
1'
0-
#175
1-
#180
b0 5
b0 A
0G
b0 $
b0 0
b0 8
b0 D
b0 (
b0 /
0#
0'
0%
0-
#185
1-
#190
b1 4
b0 3
0-
#195
1-
#200
b1 $
b1 0
b1 8
b1 D
1#
1%
0-
#205
b100 Q
0V
b1 [
19
1-
#210
1G
1'
0-
#215
b10 [
1V
0+
b100 P
b1 Z
1-
#220
0G
b0 $
b0 0
b0 8
b0 D
0#
0'
0%
0-
#225
b11010010111111100010100000000000000000000000000000000000000000000000000000000000000000000000000000000000000000000000000000000000 Y
1S
b1111 [
b11010010111111100010100000000000 *
b11010010111111100010100000000000 ;
b11010010111111100010100000000000 O
b11010010111111100010100000000000 ^
1+
b10 Z
09
1-
#230
0-
#235
0S
1R
b11010010111111100010100000000000000000000000000000000000000000000000000000000000000000000000000000000000000000000000000000000000 X
b1111 Z
1-
#240
0-
#245
0R
1-
